[
    {
        "district": "浦东",
        "name":"碧之海 崂山路",
        "link": "https://t.me/ljzty9999"
    },
    {
        "district": "浦东",
        "name":"虹之间 沪南路",
        "link": "https://t.me/ljzty9999"
    },
    {
        "district": "浦东",
        "name":"浪淘沙公馆",
        "link": "https://t.me/ljzyy88888"
    },
    {
        "district": "浦东",
        "name":"云沐 杨思",
        "link": "https://t.me/yyzlj"
    },
    {
        "district": "浦东",
        "name":"个人居家 周浦",
        "link": ""
    }
]